tooz/__init__.py
tooz/_retry.py
tooz/coordination.py
tooz/hashring.py
tooz/locking.py
tooz/partitioner.py
tooz/utils.py
tooz/drivers/__init__.py
tooz/drivers/consul.py
tooz/drivers/etcd.py
tooz/drivers/etcd3gw.py
tooz/drivers/file.py
tooz/drivers/ipc.py
tooz/drivers/kubernetes.py
tooz/drivers/memcached.py
tooz/drivers/mysql.py
tooz/drivers/pgsql.py
tooz/drivers/redis.py
tooz/drivers/zake.py
tooz/drivers/zookeeper.py
tooz/tests/__init__.py
tooz/tests/test_coordination.py
tooz/tests/test_hashring.py
tooz/tests/test_kubernetes.py
tooz/tests/test_partitioner.py
tooz/tests/test_utils.py
tooz/tests/drivers/__init__.py
tooz/tests/drivers/test_etcd.py
tooz/tests/drivers/test_etcd3gw.py
tooz/tests/drivers/test_file.py
tooz/tests/drivers/test_memcache.py
tooz/tests/drivers/test_mysql.py
tooz/tests/drivers/test_postgresql.py
tooz-7.0.0.dist-info/AUTHORS
tooz-7.0.0.dist-info/LICENSE
tooz-7.0.0.dist-info/METADATA
tooz-7.0.0.dist-info/WHEEL
tooz-7.0.0.dist-info/entry_points.txt
tooz-7.0.0.dist-info/pbr.json
tooz-7.0.0.dist-info/top_level.txt
tooz-7.0.0.dist-info/RECORD
